{"configuration":{},"documentation":{},"id":91929,"lastModifiedAgent":"structurizr-cloud/diagram-editor/f9c6eaed-e079-4a43-8f97-5e6deff32069","lastModifiedDate":"2024-06-14T22:47:15Z","lastModifiedUser":"u20211b995@upc.edu.pe","model":{"people":[{"description":"User who manages the system","id":"1","location":"Unspecified","name":"Administrator","relationships":[{"description":"Por que usa el sistema?","destinationId":"3","id":"8","sourceId":"1","tags":"Relationship"},{"description":"Use","destinationId":"14","id":"20","sourceId":"1","tags":"Relationship"},{"description":"Use","destinationId":"15","id":"22","sourceId":"1","tags":"Relationship"},{"description":"Use","destinationId":"16","id":"24","sourceId":"1","tags":"Relationship"}],"tags":"Element,Person"},{"description":"User who consumes the system","id":"2","location":"Unspecified","name":"Subscriber","relationships":[{"description":"Por que usa el sistema?","destinationId":"3","id":"9","sourceId":"2","tags":"Relationship"},{"description":"Use","destinationId":"14","id":"21","sourceId":"2","tags":"Relationship"},{"description":"Use","destinationId":"15","id":"23","sourceId":"2","tags":"Relationship"},{"description":"Use","destinationId":"16","id":"25","sourceId":"2","tags":"Relationship"}],"tags":"Element,Person"}],"softwareSystems":[{"containers":[{"description":"Some description","documentation":{},"id":"14","name":"Some Container","relationships":[{"description":"API Request","destinationId":"19","id":"26","sourceId":"14","tags":"Relationship","technology":"JSON HTTPS"}],"tags":"Element,Container","technology":"Some Technology"},{"documentation":{},"id":"15","name":"Mobile App","relationships":[{"description":"API Request","destinationId":"19","id":"27","sourceId":"15","tags":"Relationship","technology":"JSON HTTPS"}],"tags":"Element,Container","technology":"Flutter"},{"documentation":{},"id":"16","name":"Web Application","relationships":[{"description":"API Request","destinationId":"19","id":"28","sourceId":"16","tags":"Relationship","technology":"JSON HTTPS"}],"tags":"Element,Container","technology":"Angular"},{"documentation":{},"id":"17","name":"Landing Page","tags":"Element,Container","technology":"Angular"},{"documentation":{},"id":"18","name":"MySQL","tags":"Element,Container","technology":"Database"},{"components":[{"documentation":{},"id":"31","name":"Domain Layer Server Connection","tags":"Element,Component","technology":"NodeJS (NestJS)"},{"documentation":{},"id":"32","name":"Interface Layer Server Connection","relationships":[{"destinationId":"34","id":"35","sourceId":"32","tags":"Relationship"}],"tags":"Element,Component","technology":"NodeJS (NestJS)"},{"documentation":{},"id":"33","name":"Infrastructure Layer Server Connection","relationships":[{"destinationId":"31","id":"38","sourceId":"33","tags":"Relationship"},{"description":"Use","destinationId":"7","id":"39","sourceId":"33","tags":"Relationship","technology":"HTTPS JSON"},{"description":"Use","destinationId":"4","id":"40","sourceId":"33","tags":"Relationship","technology":"HTTPS JSON"},{"description":"Use","destinationId":"6","id":"41","sourceId":"33","tags":"Relationship","technology":"HTTPS JSON"},{"description":"Use","destinationId":"5","id":"42","sourceId":"33","tags":"Relationship","technology":"HTTPS JSON"}],"tags":"Element,Component","technology":"NodeJS (NestJS)"},{"documentation":{},"id":"34","name":"Application Layer Server Connection","relationships":[{"destinationId":"31","id":"36","sourceId":"34","tags":"Relationship"},{"destinationId":"33","id":"37","sourceId":"34","tags":"Relationship"}],"tags":"Element,Component","technology":"NodeJS (NestJS)"}],"documentation":{},"id":"19","name":"Api Rest","relationships":[{"description":"API Request","destinationId":"7","id":"29","sourceId":"19","tags":"Relationship","technology":"JSON HTTPS"},{"description":"API Request","destinationId":"4","id":"30","sourceId":"19","tags":"Relationship","technology":"JSON HTTPS"}],"tags":"Element,Container","technology":".NET 8"}],"description":"System to manage tickets","documentation":{},"id":"3","location":"Unspecified","name":"System","relationships":[{"description":"Por que usa el sistema?","destinationId":"4","id":"10","sourceId":"3","tags":"Relationship"},{"description":"Por que usa el sistema?","destinationId":"5","id":"11","sourceId":"3","tags":"Relationship"},{"description":"Por que usa el sistema?","destinationId":"6","id":"12","sourceId":"3","tags":"Relationship"},{"description":"Por que usa el sistema?","destinationId":"7","id":"13","sourceId":"3","tags":"Relationship"}],"tags":"Element,Software System"},{"description":"Use to send SMS through the WhatsApp API","documentation":{},"id":"4","location":"Unspecified","name":"Twilio","tags":"Element,Software System"},{"description":"Use to send emails","documentation":{},"id":"5","location":"Unspecified","name":"SendGrind","tags":"Element,Software System"},{"description":"Use to pay tickets","documentation":{},"id":"6","location":"Unspecified","name":"Paypal","tags":"Element,Software System"},{"description":"Use the system to get information about the games","documentation":{},"id":"7","location":"Unspecified","name":"FIFA","tags":"Element,Software System"}]},"name":"C4 Model Design - PC 2 - Jonatan Acuña","revision":118,"views":{"componentViews":[{"containerId":"19","description":"API Rest Component Diagram","dimensions":{"height":2758,"width":4220},"elements":[{"id":"4","x":1295,"y":2129},{"id":"5","x":2045,"y":2129},{"id":"6","x":2795,"y":2129},{"id":"7","x":3545,"y":2129},{"id":"31","x":437,"y":2129},{"id":"32","x":483,"y":329},{"id":"33","x":637,"y":1529},{"id":"34","x":483,"y":929}],"externalContainerBoundariesVisible":false,"key":"API Rest Component Diagram","order":1,"paperSize":"A3_Landscape","relationships":[{"id":"35"},{"id":"36","vertices":[{"x":487,"y":1529},{"x":487,"y":1829}]},{"id":"37"},{"id":"38"},{"id":"39","vertices":[{"x":3395,"y":2129}]},{"id":"40"},{"id":"41","vertices":[{"x":2645,"y":2129}]},{"id":"42"}],"title":"API Rest Component Diagram"}],"configuration":{"branding":{},"lastSavedView":"API Rest Component Diagram","metadataSymbols":"SquareBrackets","styles":{},"terminology":{},"viewSortOrder":"Default"},"containerViews":[{"description":"Diagram Containers","dimensions":{"height":2516,"width":5129},"elements":[{"id":"1","x":2204,"y":208},{"id":"2","x":2954,"y":208},{"id":"4","x":2204,"y":2008},{"id":"5","x":3704,"y":208},{"id":"6","x":4454,"y":208},{"id":"7","x":2954,"y":2008},{"id":"14","x":3329,"y":808},{"id":"15","x":2579,"y":808},{"id":"16","x":1829,"y":808},{"id":"17","x":1079,"y":808},{"id":"18","x":329,"y":808},{"id":"19","x":2579,"y":1408}],"externalSoftwareSystemBoundariesVisible":false,"key":"Containers","order":1,"paperSize":"A2_Landscape","relationships":[{"id":"20","vertices":[{"x":3179,"y":704}]},{"id":"21"},{"id":"22"},{"id":"23"},{"id":"24"},{"id":"25","vertices":[{"x":2429,"y":704}]},{"id":"26"},{"id":"27"},{"id":"28"},{"id":"29"},{"id":"30"}],"softwareSystemId":"3"}],"systemContextViews":[{"description":"Diagram Context","dimensions":{"height":1916,"width":3116},"elements":[{"id":"1","x":958,"y":208},{"id":"2","x":1708,"y":208},{"id":"3","x":1333,"y":808},{"id":"4","x":208,"y":1408},{"id":"5","x":958,"y":1408},{"id":"6","x":1708,"y":1408},{"id":"7","x":2458,"y":1408}],"enterpriseBoundaryVisible":true,"key":"Context","order":1,"paperSize":"A4_Landscape","relationships":[{"id":"10"},{"id":"11"},{"id":"12"},{"id":"13"},{"id":"8"},{"id":"9"}],"softwareSystemId":"3"}]}}